RAM/DualPortRAM.sv
module DualPortRAM #(
    parameter AW = 8,
    parameter DW = 32,
    parameter SETPRIORITY = 0        // 0 = No priority, 1 = A port priority , 2 = B port priority for writing
)(
    input  logic          clk,
    
    input  logic          aWrite,
    input  logic          aEn,
    input  logic [AW-1:0] aAddr,
    input  logic [DW-1:0] aWriteData,
    output logic [DW-1:0] aReadData,

    input  logic          bWrite,
    input  logic          bEn,
    input  logic [AW-1:0] bAddr,
    input  logic [DW-1:0] bWriteData,
    output logic [DW-1:0] bReadData,
    output                conflict
);

logic [DW-1:0] mem [(1<<AW)-1:0];
logic conflictDetected;

assign conflictDetected = (aAddr == bAddr) && (aWrite && bWrite);
assign conflict         = (SETPRIORITY == 0) ? conflictDetected : 0;

always_ff @(posedge clk) 
begin
  if (conflictDetected) 
  begin
    case (SETPRIORITY)
      1: if (aEn && aWrite) mem[aAddr] <= aWriteData;
      2: if (bEn && bWrite) mem[bAddr] <= bWriteData;
      default: ; // Do nothing on true conflict
    endcase
  end else 
  begin
    if (aEn && aWrite) mem[aAddr] <= aWriteData;
    if (bEn && bWrite) mem[bAddr] <= bWriteData;
  end
end

assign aReadData = aEn ? mem[aAddr] : '0;
assign bReadData = bEn ? mem[bAddr] : '0;

endmodule

RAM/DualPortRAM_tb.sv
`timescale 1ns/1ps

module DualPortRAM_tb;

  // Parameters
  localparam AW = 8;
  localparam DW = 32;
  localparam DEPTH = 1 << AW;

  // Clock
  logic clk = 0;
  always #5 clk = ~clk;

  // Port A signals
  logic          aWrite, aEn;
  logic [AW-1:0] aAddr;
  logic [DW-1:0] aWriteData;
  logic [DW-1:0] aReadData;

  // Port B signals
  logic          bWrite, bEn;
  logic [AW-1:0] bAddr;
  logic [DW-1:0] bWriteData;
  logic [DW-1:0] bReadData;
  logic          conflict;

  // DUT Instance
  DualPortRAM #(
    .AW(AW),
    .DW(DW),
    .SETPRIORITY(2)
  ) dut (
    .clk         (clk),
    .aWrite      (aWrite),
    .aEn         (aEn),
    .aAddr       (aAddr),
    .aWriteData  (aWriteData),
    .aReadData   (aReadData),
    .bWrite      (bWrite),
    .bEn         (bEn),
    .bAddr       (bAddr),
    .bWriteData  (bWriteData),
    .bReadData   (bReadData),
    .conflict    (conflict)
  );

  // Stimulus
  initial begin
    $display("Starting DualPortRAM test...");
    $dumpfile("dualport_ram.vcd");
    $dumpvars(0, DualPortRAM_tb);

    // Reset-like idle phase
    aWrite = 0; aEn = 0; aAddr = 0; aWriteData = 0;
    bWrite = 0; bEn = 0; bAddr = 0; bWriteData = 0;
    repeat (2) @(posedge clk);
    #5;
    ta_Back_to_Back_writes();
    #5;
    ta_Simultaneous_writes();
    #5;
    ta_conflicted_write();

    $display("Test complete.");
    $finish;
  end
  
  initial begin
    $monitor("Time: %0t | conflict set : %b", $time, conflict);
  end

    task ta_Back_to_Back_writes();
       $display("==== Starting Back to Back Writes ====");
      // Write from Port A to locations 0-3
      for (int i = 0; i < 4; i++) begin
        @(posedge clk);
        aEn = 1; aWrite = 1; aAddr = i; aWriteData = 32'hA0000000 + i;
      end
      @(posedge clk); aEn = 0; aWrite = 0;
  
      // Write from Port B to locations 4-7
      for (int i = 0; i < 4; i++) begin
        @(posedge clk);
        bEn = 1; bWrite = 1; bAddr = i + 4; bWriteData = 32'hB0000000 + i;
      end
      @(posedge clk); bEn = 0; bWrite = 0;
  
      // Read back from A
      for (int i = 0; i < 4; i++) begin
        @(posedge clk);
        aEn = 1; aWrite = 0; aAddr = i;
        @(posedge clk);
        $display("Port A Read Addr %0d: %h", i, aReadData);
        assert(aReadData == (32'hA0000000 + i)) else $fatal("Mismatch on A[%0d]", i);
      end
      aEn = 0;
  
      // Read back from B
      for (int i = 0; i < 4; i++) begin
        @(posedge clk);
        bEn = 1; bWrite = 0; bAddr = i + 4;
        @(posedge clk);
        $display("Port B Read Addr %0d: %h", i+4, bReadData);
        assert(bReadData == (32'hB0000000 + i)) else $fatal("Mismatch on B[%0d]", i+4);
      end
      bEn = 0;
    endtask

    task ta_Simultaneous_writes();
      $display("==== Starting Simultaneous Writes ====");
      // Write from Port A to locations 20-23 and from Port B to locations 24 to 27 
      for (int i = 20; i < 24; i++) begin
        @(posedge clk);
        aEn = 1; aWrite = 1; aAddr = i; aWriteData = 32'hA000B000 + i;
        bEn = 1; bWrite = 1; bAddr = i + 4; bWriteData = 32'hB000A000 + i;
      end
      @(posedge clk); aEn = 0; aWrite = 0; bEn = 0; bWrite = 0;
  
      // Read back from A and B
      for (int i = 20; i < 24; i++) begin
        @(posedge clk);
        aEn = 1; aWrite = 0; aAddr = i;
        bEn = 1; bWrite = 0; bAddr = i + 4;
        @(posedge clk);
        $display("Port A Read Addr %0d: %h", i, aReadData);
        assert(aReadData == (32'hA000B000 + i)) else $fatal("Mismatch on A[%0d]", i);
        $display("Port B Read Addr %0d: %h", i+4, bReadData);
        assert(bReadData == (32'hB000A000 + i)) else $fatal("Mismatch on B[%0d]", i+4);
      end
      aEn = 0;
      bEn = 0;
    endtask

    task ta_conflicted_write();
      $display("==== Starting conflicted Write ====");
      // Conflict test — both write to same address
      @(posedge clk);
      aEn = 1; aWrite = 1; aAddr = 8; aWriteData = 32'hDEADBEAF;
      bEn = 1; bWrite = 1; bAddr = 8; bWriteData = 32'hCAFEBABE;
      @(posedge clk);
      aWrite = 0; bWrite = 0;
      $display("A wrote data %h to Addr %h, and B wrote data %h to Addr %h",aWriteData,aAddr,bWriteData,bAddr);
  
      // Read from both
      @(posedge clk);
      aEn = 1; aAddr = 8;
      bEn = 1; bAddr = 8;
      @(posedge clk);
      $display("After conflict: A Read Addr %h = %h, B Read Addr %h = %h", aAddr, aReadData, bAddr, bReadData);
      assert(aReadData == 32'hCAFEBABE && bReadData == 32'hCAFEBABE) else $fatal("Conflict priority logic failed. Expected B's data to win.");
    endtask


endmodule

RAM/dualport_ram.vcd
$date
	Thu Jul 24 12:16:15 2025
$end
$version
	Questa Intel Starter FPGA Edition Version 2024.3
$end
$timescale
	1ps
$end

$scope module DualPortRAM_tb $end
$var parameter 32 ! AW $end
$var parameter 32 " DW $end
$var parameter 32 # DEPTH $end
$var reg 1 $ clk $end
$var reg 1 % aWrite $end
$var reg 1 & aEn $end
$var reg 8 ' aAddr [7:0] $end
$var reg 32 ( aWriteData [31:0] $end
$var reg 32 ) aReadData [31:0] $end
$var reg 1 * bWrite $end
$var reg 1 + bEn $end
$var reg 8 , bAddr [7:0] $end
$var reg 32 - bWriteData [31:0] $end
$var reg 32 . bReadData [31:0] $end
$var reg 1 / conflict $end

$scope task ta_Back_to_Back_writes $end
$upscope $end

$scope task ta_Simultaneous_writes $end
$upscope $end

$scope task ta_conflicted_write $end
$upscope $end

$scope module dut $end
$var parameter 32 0 AW $end
$var parameter 32 1 DW $end
$var parameter 32 2 SETPRIORITY $end
$var wire 1 3 clk $end
$var wire 1 4 aWrite $end
$var wire 1 5 aEn $end
$var wire 1 6 aAddr [7] $end
$var wire 1 7 aAddr [6] $end
$var wire 1 8 aAddr [5] $end
$var wire 1 9 aAddr [4] $end
$var wire 1 : aAddr [3] $end
$var wire 1 ; aAddr [2] $end
$var wire 1 < aAddr [1] $end
$var wire 1 = aAddr [0] $end
$var wire 1 > aWriteData [31] $end
$var wire 1 ? aWriteData [30] $end
$var wire 1 @ aWriteData [29] $end
$var wire 1 A aWriteData [28] $end
$var wire 1 B aWriteData [27] $end
$var wire 1 C aWriteData [26] $end
$var wire 1 D aWriteData [25] $end
$var wire 1 E aWriteData [24] $end
$var wire 1 F aWriteData [23] $end
$var wire 1 G aWriteData [22] $end
$var wire 1 H aWriteData [21] $end
$var wire 1 I aWriteData [20] $end
$var wire 1 J aWriteData [19] $end
$var wire 1 K aWriteData [18] $end
$var wire 1 L aWriteData [17] $end
$var wire 1 M aWriteData [16] $end
$var wire 1 N aWriteData [15] $end
$var wire 1 O aWriteData [14] $end
$var wire 1 P aWriteData [13] $end
$var wire 1 Q aWriteData [12] $end
$var wire 1 R aWriteData [11] $end
$var wire 1 S aWriteData [10] $end
$var wire 1 T aWriteData [9] $end
$var wire 1 U aWriteData [8] $end
$var wire 1 V aWriteData [7] $end
$var wire 1 W aWriteData [6] $end
$var wire 1 X aWriteData [5] $end
$var wire 1 Y aWriteData [4] $end
$var wire 1 Z aWriteData [3] $end
$var wire 1 [ aWriteData [2] $end
$var wire 1 \ aWriteData [1] $end
$var wire 1 ] aWriteData [0] $end
$var reg 32 ^ aReadData [31:0] $end
$var wire 1 _ bWrite $end
$var wire 1 ` bEn $end
$var wire 1 a bAddr [7] $end
$var wire 1 b bAddr [6] $end
$var wire 1 c bAddr [5] $end
$var wire 1 d bAddr [4] $end
$var wire 1 e bAddr [3] $end
$var wire 1 f bAddr [2] $end
$var wire 1 g bAddr [1] $end
$var wire 1 h bAddr [0] $end
$var wire 1 i bWriteData [31] $end
$var wire 1 j bWriteData [30] $end
$var wire 1 k bWriteData [29] $end
$var wire 1 l bWriteData [28] $end
$var wire 1 m bWriteData [27] $end
$var wire 1 n bWriteData [26] $end
$var wire 1 o bWriteData [25] $end
$var wire 1 p bWriteData [24] $end
$var wire 1 q bWriteData [23] $end
$var wire 1 r bWriteData [22] $end
$var wire 1 s bWriteData [21] $end
$var wire 1 t bWriteData [20] $end
$var wire 1 u bWriteData [19] $end
$var wire 1 v bWriteData [18] $end
$var wire 1 w bWriteData [17] $end
$var wire 1 x bWriteData [16] $end
$var wire 1 y bWriteData [15] $end
$var wire 1 z bWriteData [14] $end
$var wire 1 { bWriteData [13] $end
$var wire 1 | bWriteData [12] $end
$var wire 1 } bWriteData [11] $end
$var wire 1 ~ bWriteData [10] $end
$var wire 1 !! bWriteData [9] $end
$var wire 1 "! bWriteData [8] $end
$var wire 1 #! bWriteData [7] $end
$var wire 1 $! bWriteData [6] $end
$var wire 1 %! bWriteData [5] $end
$var wire 1 &! bWriteData [4] $end
$var wire 1 '! bWriteData [3] $end
$var wire 1 (! bWriteData [2] $end
$var wire 1 )! bWriteData [1] $end
$var wire 1 *! bWriteData [0] $end
$var reg 32 +! bReadData [31:0] $end
$var wire 1 ,! conflict $end
$var reg 1 -! conflictDetected $end
$upscope $end
$upscope $end
$enddefinitions $end
#0
$dumpvars
0$
0%
0&
b0 '
b0 (
b0 )
0*
0+
b0 ,
b0 -
b0 .
0/
b0 ^
b0 +!
0-!
b1000 !
b100000 "
b100000000 #
b1000 0
b100000 1
b10 2
0*!
0)!
0(!
0'!
0&!
0%!
0$!
0#!
0"!
0!!
0~
0}
0|
0{
0z
0y
0x
0w
0v
0u
0t
0s
0r
0q
0p
0o
0n
0m
0l
0k
0j
0i
0h
0g
0f
0e
0d
0c
0b
0a
0`
0_
0]
0\
0[
0Z
0Y
0X
0W
0V
0U
0T
0S
0R
0Q
0P
0O
0N
0M
0L
0K
0J
0I
0H
0G
0F
0E
0D
0C
0B
0A
0@
0?
0>
0=
0<
0;
0:
09
08
07
06
05
04
03
0,!
$end
#5000
1$
13
#10000
0$
03
#15000
1$
13
#20000
0$
03
#25000
1$
13
1&
1%
b10100000000000000000000000000000 (
15
14
1@
1>
bx ^
bx )
#30000
0$
03
#35000
1$
13
b1 '
b10100000000000000000000000000001 (
1]
1=
#40000
0$
03
#45000
1$
13
b10 '
b10100000000000000000000000000010 (
0]
1\
0=
1<
#50000
0$
03
#55000
1$
13
b11 '
b10100000000000000000000000000011 (
1]
1=
#60000
0$
03
#65000
1$
13
0&
0%
05
04
b0 ^
b0 )
#70000
0$
03
#75000
1$
13
1+
1*
b100 ,
b10110000000000000000000000000000 -
1`
1_
1l
1k
1i
1f
bx +!
bx .
#80000
0$
03
#85000
1$
13
b101 ,
b10110000000000000000000000000001 -
1*!
1h
#90000
0$
03
#95000
1$
13
b110 ,
b10110000000000000000000000000010 -
0*!
1)!
0h
1g
#100000
0$
03
#105000
1$
13
b111 ,
b10110000000000000000000000000011 -
1*!
1h
#110000
0$
03
#115000
1$
13
0+
0*
0`
0_
b0 +!
b0 .
#120000
0$
03
#125000
1$
13
1&
b0 '
15
0=
0<
b10100000000000000000000000000000 ^
b10100000000000000000000000000000 )
#130000
0$
03
#135000
1$
13
#140000
0$
03
#145000
1$
13
b1 '
1=
b10100000000000000000000000000001 ^
b10100000000000000000000000000001 )
#150000
0$
03
#155000
1$
13
#160000
0$
03
#165000
1$
13
b10 '
0=
1<
b10100000000000000000000000000010 ^
b10100000000000000000000000000010 )
#170000
0$
03
#175000
1$
13
#180000
0$
03
#185000
1$
13
b11 '
1=
b10100000000000000000000000000011 ^
b10100000000000000000000000000011 )
#190000
0$
03
#195000
1$
13
0&
05
b0 ^
b0 )
#200000
0$
03
#205000
1$
13
1+
b100 ,
1`
0h
0g
b10110000000000000000000000000000 +!
b10110000000000000000000000000000 .
#210000
0$
03
#215000
1$
13
#220000
0$
03
#225000
1$
13
b101 ,
1h
b10110000000000000000000000000001 +!
b10110000000000000000000000000001 .
#230000
0$
03
#235000
1$
13
#240000
0$
03
#245000
1$
13
b110 ,
0h
1g
b10110000000000000000000000000010 +!
b10110000000000000000000000000010 .
#250000
0$
03
#255000
1$
13
#260000
0$
03
#265000
1$
13
b111 ,
1h
b10110000000000000000000000000011 +!
b10110000000000000000000000000011 .
#270000
0$
03
#275000
1$
13
0+
0`
b0 +!
b0 .
#280000
0$
03
#285000
1$
13
1&
1%
b10100 '
b10100000000000001011000000010100 (
1+
1*
b11000 ,
b10110000000000001010000000010100 -
15
14
1`
1_
0*!
0)!
1(!
1&!
1{
1y
0h
0g
0f
1e
1d
0]
0\
1[
1Y
1Q
1P
1N
0=
0<
1;
19
bx +!
bx ^
bx )
bx .
#290000
0$
03
#295000
1$
13
b10101 '
b10100000000000001011000000010101 (
b11001 ,
b10110000000000001010000000010101 -
1*!
1h
1]
1=
#300000
0$
03
#305000
1$
13
b10110 '
b10100000000000001011000000010110 (
b11010 ,
b10110000000000001010000000010110 -
0*!
1)!
0h
1g
0]
1\
0=
1<
#310000
0$
03
#315000
1$
13
b10111 '
b10100000000000001011000000010111 (
b11011 ,
b10110000000000001010000000010111 -
1*!
1h
1]
1=
#320000
0$
03
#325000
1$
13
0&
0%
0+
0*
05
04
0`
0_
b0 +!
b0 ^
b0 )
b0 .
#330000
0$
03
#335000
1$
13
1&
b10100 '
1+
b11000 ,
15
1`
0h
0g
0=
0<
b10110000000000001010000000010100 +!
b10100000000000001011000000010100 ^
b10100000000000001011000000010100 )
b10110000000000001010000000010100 .
#340000
0$
03
#345000
1$
13
#350000
0$
03
#355000
1$
13
b10101 '
b11001 ,
1h
1=
b10110000000000001010000000010101 +!
b10100000000000001011000000010101 ^
b10100000000000001011000000010101 )
b10110000000000001010000000010101 .
#360000
0$
03
#365000
1$
13
#370000
0$
03
#375000
1$
13
b10110 '
b11010 ,
0h
1g
0=
1<
b10110000000000001010000000010110 +!
b10100000000000001011000000010110 ^
b10100000000000001011000000010110 )
b10110000000000001010000000010110 .
#380000
0$
03
#385000
1$
13
#390000
0$
03
#395000
1$
13
b10111 '
b11011 ,
1h
1=
b10110000000000001010000000010111 +!
b10100000000000001011000000010111 ^
b10100000000000001011000000010111 )
b10110000000000001010000000010111 .
#400000
0$
03
#405000
1$
13
0&
0+
05
0`
b0 +!
b0 ^
b0 )
b0 .
#410000
0$
03
#415000
1$
13
1&
1%
b1000 '
b11011110101011011011111010101111 (
1+
1*
b1000 ,
b11001010111111101011101010111110 -
15
14
1`
1_
0*!
1'!
1%!
1#!
1!!
1}
1|
1w
1v
1u
1t
1s
1r
1q
1o
1m
0l
0k
1j
0h
0g
0d
1Z
0Y
1X
1V
1T
1S
1R
1M
1K
1J
1H
1F
1D
1C
1B
1A
0@
1?
0=
0<
0;
1:
09
bx +!
1-!
bx ^
bx )
bx .
#420000
0$
03
#425000
1$
13
0%
0*
04
0_
0-!
b11001010111111101011101010111110 ^
b11001010111111101011101010111110 +!
b11001010111111101011101010111110 .
b11001010111111101011101010111110 )
